movoid_timer/__init__.py
movoid_timer/timeout.py
movoid_timer/timer.py
movoid_timer-1.0.4.dist-info/METADATA
movoid_timer-1.0.4.dist-info/WHEEL
movoid_timer-1.0.4.dist-info/top_level.txt
movoid_timer-1.0.4.dist-info/RECORD
