Metadata-Version: 2.1
Name: movoid_timer
Version: 1.0.4
Summary: create timer to record time
Home-page: 
Author: movoid
Author-email: bobrobotsun@163.com
